nfceget/BadQRCodeError.py
nfceget/QrCodeLinkNotFound.py
nfceget/StateInvalidError.py
nfceget/__init__.py
nfceget/app.py
nfceget/htmlNfce.py
nfceget/util.py
nfceget/pr/__init__.py
nfceget/pr/notaparana.py
nfceget/pr/receitaestadual.py
tests/__init__.py
tests/test_app.py
tests/test_pr.py
tests/test_utils.py
nfceget-1.1.2.dist-info/LICENSE
nfceget-1.1.2.dist-info/METADATA
nfceget-1.1.2.dist-info/WHEEL
nfceget-1.1.2.dist-info/top_level.txt
nfceget-1.1.2.dist-info/RECORD
