Metadata-Version: 2.1
Name: nfceget
Version: 1.1.2
Summary: Pacote para recuperar uma NFCE (nota fiscal consumidor eletronica) e transformar em json.
Home-page: https://github.com/brunopenso/python-nfce-get
Author: Bruno Penso
License: UNKNOWN
Platform: UNKNOWN
Classifier: Programming Language :: Python :: 3
Classifier: License :: OSI Approved :: MIT License
Classifier: Operating System :: OS Independent
Requires-Python: >=3.6
License-File: LICENSE
